pytest_wholenodeid.py
pytest_wholenodeid-0.2.dist-info/WHEEL
pytest_wholenodeid-0.2.dist-info/entry_points.txt
pytest_wholenodeid-0.2.dist-info/top_level.txt
pytest_wholenodeid-0.2.dist-info/RECORD
pytest_wholenodeid-0.2.dist-info/METADATA
pytest_wholenodeid-0.2.dist-info/zip-safe
pytest_wholenodeid-0.2.dist-info/metadata.json
pytest_wholenodeid-0.2.dist-info/DESCRIPTION.rst
