Metadata-Version: 2.0
Name: pytest-wholenodeid
Version: 0.2
Summary: pytest addon for displaying the whole node id for failures
Home-page: https://github.com/willkg/pytest-wholenodeid
Author: Will Kahn-Greene
Author-email: willkg@bluesock.org
License: Simplified BSD License
Keywords: py.test pytest
Platform: UNKNOWN
Classifier: Development Status :: 4 - Beta
Classifier: Environment :: Console
Classifier: License :: OSI Approved :: BSD License
Classifier: Operating System :: MacOS :: MacOS X
Classifier: Operating System :: POSIX
Classifier: Operating System :: POSIX :: Linux
Classifier: Operating System :: Unix
Classifier: Topic :: Software Development :: Testing
Classifier: Topic :: Software Development :: Libraries
Classifier: Topic :: Utilities
Classifier: Programming Language :: Python :: 2
Classifier: Programming Language :: Python :: 2.7
Requires-Dist: pytest (>=2.0)
